triton/__init__.py
triton/_internal_testing.py
triton/errors.py
triton/testing.py
triton/_C/libentry_ascend.so
triton/_C/libtriton.so
triton/backends/__init__.py
triton/backends/compiler.py
triton/backends/driver.py
triton/backends/ascend/__init__.py
triton/backends/ascend/bishengir-hfusion-ods-yaml-gen
triton/backends/ascend/compiler.py
triton/backends/ascend/cpu_driver.py
triton/backends/ascend/driver.py
triton/backends/ascend/name.conf
triton/backends/ascend/npu_utils.cpp
triton/backends/ascend/triton-adapter-opt
triton/backends/ascend/utils.py
triton/compiler/__init__.py
triton/compiler/code_generator.py
triton/compiler/compiler.py
triton/compiler/errors.py
triton/compiler/make_launcher.py
triton/language/__init__.py
triton/language/_utils.py
triton/language/core.py
triton/language/math.py
triton/language/random.py
triton/language/semantic.py
triton/language/standard.py
triton/language/extra/__init__.py
triton/language/extra/libdevice.py
triton/language/extra/ascend/__init__.py
triton/language/extra/ascend/libdevice.py
triton/runtime/__init__.py
triton/runtime/autotiling_tuner.py
triton/runtime/autotuner.py
triton/runtime/build.py
triton/runtime/cache.py
triton/runtime/code_cache.py
triton/runtime/driver.py
triton/runtime/errors.py
triton/runtime/interpreter.py
triton/runtime/jit.py
triton/runtime/libentry.py
triton/runtime/tile_generator.py
triton/runtime/utils.py
triton/tools/__init__.py
triton/tools/build_extern.py
triton/tools/compile.c
triton/tools/compile.h
triton/tools/compile.py
triton/tools/disasm.py
triton/tools/experimental_descriptor.py
triton/tools/link.py
triton/triton_patch/testing.py
triton/triton_patch/compiler/code_generator.py
triton/triton_patch/compiler/compiler.py
triton/triton_patch/compiler/errors.py
triton/triton_patch/language/_utils.py
triton/triton_patch/language/core.py
triton/triton_patch/language/math.py
triton/triton_patch/language/semantic.py
triton_ascend-3.2.0rc4.dist-info/METADATA
triton_ascend-3.2.0rc4.dist-info/WHEEL
triton_ascend-3.2.0rc4.dist-info/top_level.txt
triton_ascend-3.2.0rc4.dist-info/RECORD
triton_ascend-3.2.0rc4.dist-info/licenses/LICENSE
