Metadata-Version: 2.4
Name: triton-ascend
Version: 3.2.0rc4
Summary: A language and compiler for custom Deep Learning operations on Ascend hardwares
Home-page: https://gitcode.com/Ascend/triton-ascend/
Keywords: Compiler,Deep Learning
License-File: LICENSE
Dynamic: description
Dynamic: description-content-type
Dynamic: home-page
Dynamic: keywords
Dynamic: license-file
Dynamic: summary
